pylibclang-stubs/_C.pyi
pylibclang_stubs-318.1.1.dist-info/METADATA
pylibclang_stubs-318.1.1.dist-info/WHEEL
pylibclang_stubs-318.1.1.dist-info/top_level.txt
pylibclang_stubs-318.1.1.dist-info/RECORD
